{"11542": {"arrival_airport_iata": "FUE", "model": "850XP", "departure_airport_iata": "BQH", "operatorId": "001w000001AKVAOAA5", "seats": "8", "price": "15910", "manufacturer": "Hawker Beechcraft", "lastDepartureTime": "2018-08-11 11:50:00", "sfAircraftId": "a09w0000011zoHRAAY", "firstDepartureTime": "2018-08-11 00:10:00"}, "11544": {"arrival_airport_iata": "BQH", "model": "Phenom 100", "departure_airport_iata": "TLN", "operatorId": "001w000001AKVAOAA5", "seats": "4", "price": "6930", "manufacturer": "Embraer", "lastDepartureTime": "2018-07-13 23:50:00", "sfAircraftId": "a09w000001WSbKoAAL", "firstDepartureTime": "2018-07-13 12:00:00"}, "11384": {"arrival_airport_iata": "TLL", "model": "Learjet 60XR", "departure_airport_iata": "VKO", "operatorId": "0012000000nArR9AAK", "seats": "7", "price": "9380", "manufacturer": "Bombardier", "lastDepartureTime": "2018-06-28 23:50:00", "sfAircraftId": "a09w000000gpemYAAQ", "firstDepartureTime": "2018-06-26 00:10:00"}, "11386": {"arrival_airport_iata": "NAP", "model": "Learjet 60XR", "departure_airport_iata": "TLL", "operatorId": "0012000000nArR9AAK", "seats": "7", "price": "17300", "manufacturer": "Bombardier", "lastDepartureTime": "2018-06-28 23:50:00", "sfAircraftId": "a09w000000gpemYAAQ", "firstDepartureTime": "2018-06-22 00:10:00"}, "11467": {"arrival_airport_iata": "PMI", "model": "Falcon 7X", "departure_airport_iata": "LTN", "operatorId": "0012000000G1IskAAF", "seats": "14", "price": "22050", "manufacturer": "Dassault", "lastDepartureTime": "2018-07-17 23:50:00", "sfAircraftId": "a09w000001C3jWxAAJ", "firstDepartureTime": "2018-07-17 00:10:00"}, "11469": {"arrival_airport_iata": "BQH", "model": "750", "departure_airport_iata": "TLN", "operatorId": "0012000000rauhDAAQ", "seats": "8", "price": "10300", "manufacturer": "Hawker Beechcraft", "lastDepartureTime": "2018-07-24 23:50:00", "sfAircraftId": "a09w000001C2o7fAAB", "firstDepartureTime": "2018-07-24 00:10:00"}, "11468": {"arrival_airport_iata": "LIN", "model": "Legacy 650", "departure_airport_iata": "MAN", "operatorId": "0012000000EjRYgAAN", "seats": "13", "price": "16110", "manufacturer": "Embraer", "lastDepartureTime": "2018-07-19 23:50:00", "sfAircraftId": "a09w000000dll9uAAA", "firstDepartureTime": "2018-07-16 00:10:00"}, "11414": {"arrival_airport_iata": "NAP", "model": "Citation Mustang", "departure_airport_iata": "NCE", "operatorId": "001w0000014VuzxAAC", "seats": "4", "price": "2510", "manufacturer": "Cessna", "lastDepartureTime": "2018-06-20 23:50:00", "sfAircraftId": "a09w000000ZjagcAAB", "firstDepartureTime": "2018-06-20 00:10:00"}, "11025": {"arrival_airport_iata": "STN", "model": "Citation Sovereign", "departure_airport_iata": "GVA", "operatorId": "0012000000G1IskAAF", "seats": "8", "price": "8580", "manufacturer": "Cessna", "lastDepartureTime": "2018-12-31 23:50:00", "sfAircraftId": "a091r00001XlEziAAF", "firstDepartureTime": "2018-12-31 00:00:00"}, "11026": {"arrival_airport_iata": "NOC", "model": "Citation XLS/XLS+", "departure_airport_iata": "LTN", "operatorId": "0012000000EjRZXAA3", "seats": "8", "price": "7000", "manufacturer": "Cessna", "lastDepartureTime": "2018-07-25 23:50:00", "sfAircraftId": "a09w000000ZmHVhAAN", "firstDepartureTime": "2018-07-25 00:00:00"}, "11020": {"arrival_airport_iata": "HAM", "model": "Citation CJ2/CJ2+", "departure_airport_iata": "LIN", "operatorId": "0012000000EjRYgAAN", "seats": "6", "price": "6600", "manufacturer": "Cessna", "lastDepartureTime": "2018-06-27 23:50:00", "sfAircraftId": "a09w000000ZkilpAAB", "firstDepartureTime": "2018-06-25 00:10:00"}, "11533": {"arrival_airport_iata": "BLL", "model": "Citation Bravo", "departure_airport_iata": "AVN", "operatorId": "0012000000EjRYfAAN", "seats": "7", "price": "9240", "manufacturer": "Cessna", "lastDepartureTime": "2018-05-31 23:50:00", "sfAircraftId": "a09w000000ZjYxRAAV", "firstDepartureTime": "2018-05-31 00:10:00"}, "11470": {"arrival_airport_iata": "BQH", "model": "Phenom 300", "departure_airport_iata": "LIN", "operatorId": "0012000000EjRYgAAN", "seats": "7", "price": "9510", "manufacturer": "Embraer", "lastDepartureTime": "2018-07-28 23:50:00", "sfAircraftId": "a09w000001C4zbSAAR", "firstDepartureTime": "2018-07-26 00:10:00"}, "9490": {"arrival_airport_iata": "MAN", "model": "Citation XLS/XLS+", "departure_airport_iata": "NCE", "operatorId": "0012000000ssgfeAAA", "seats": "8", "price": "11750", "manufacturer": "Cessna", "lastDepartureTime": "2019-05-17 23:00:00", "sfAircraftId": "a09w000000Zkm17AAB", "firstDepartureTime": "2018-05-17 02:00:00"}, "11036": {"arrival_airport_iata": "LIN", "model": "Citation XLS/XLS+", "departure_airport_iata": "OLB", "operatorId": "0012000000EjRYgAAN", "seats": "8", "price": "6600", "manufacturer": "Cessna", "lastDepartureTime": "2018-08-27 23:50:00", "sfAircraftId": "a09w000000ZjaPqAAJ", "firstDepartureTime": "2018-08-24 00:00:00"}, "11034": {"arrival_airport_iata": "HAM", "model": "Citation CJ3", "departure_airport_iata": "LIN", "operatorId": "0012000000EjRYgAAN", "seats": "7", "price": "7790", "manufacturer": "Cessna", "lastDepartureTime": "2018-12-08 23:50:00", "sfAircraftId": "a09w000000ZjaPgAAJ", "firstDepartureTime": "2018-12-05 00:00:00"}, "11035": {"arrival_airport_iata": "LIN", "model": "Citation CJ2/CJ2+", "departure_airport_iata": "IBZ", "operatorId": "0012000000EjRYgAAN", "seats": "6", "price": "7530", "manufacturer": "Cessna", "lastDepartureTime": "2018-10-01 23:50:00", "sfAircraftId": "a09w000000c7XiKAAU", "firstDepartureTime": "2018-09-28 00:00:00"}, "11600": {"arrival_airport_iata": "VKO", "model": "ACJ319", "departure_airport_iata": "ALA", "operatorId": "0012000000AFXRuAAP", "seats": "19", "price": "74500", "manufacturer": "Airbus", "lastDepartureTime": "2018-07-15 23:50:00", "sfAircraftId": "a09w000000ZkZltAAF", "firstDepartureTime": "2018-07-14 00:10:00"}, "11651": {"arrival_airport_iata": "LTN", "model": "Citation XLS/XLS+", "departure_airport_iata": "NAP", "operatorId": "0012000000G1IskAAF", "seats": "8", "price": "14130", "manufacturer": "Cessna", "lastDepartureTime": "2018-07-25 23:50:00", "sfAircraftId": "a09w000001XAjoXAAT", "firstDepartureTime": "2018-07-25 00:10:00"}, "10782": {"arrival_airport_iata": "DUS", "model": "Citation CJ2/CJ2+", "departure_airport_iata": "LIN", "operatorId": "0012000000EjRYgAAN", "seats": "6", "price": "5420", "manufacturer": "Cessna", "lastDepartureTime": "2018-09-28 23:50:00", "sfAircraftId": "a09w000000c7XiKAAU", "firstDepartureTime": "2018-09-26 00:10:00"}, "10781": {"arrival_airport_iata": "LBA", "model": "Legacy 600", "departure_airport_iata": "LIN", "operatorId": "0012000000EjRYgAAN", "seats": "13", "price": "13600", "manufacturer": "Embraer", "lastDepartureTime": "2018-09-19 23:50:00", "sfAircraftId": "a09w000000gr0RgAAI", "firstDepartureTime": "2018-09-17 00:10:00"}, "11216": {"arrival_airport_iata": "BQH", "model": "Citation XLS/XLS+", "departure_airport_iata": "SKG", "operatorId": "0012000000vixXYAAY", "seats": "8", "price": "16770", "manufacturer": "Cessna", "lastDepartureTime": "2018-08-13 23:50:00", "sfAircraftId": "a091r00001YcqYhAAJ", "firstDepartureTime": "2018-08-13 00:10:00"}, "11217": {"arrival_airport_iata": "BQH", "model": "850XP", "departure_airport_iata": "PMI", "operatorId": "001w000001AKVAOAA5", "seats": "8", "price": "11880", "manufacturer": "Hawker Beechcraft", "lastDepartureTime": "2018-08-19 23:50:00", "sfAircraftId": "a09w000000mWNc6AAG", "firstDepartureTime": "2018-08-19 00:10:00"}, "11215": {"arrival_airport_iata": "SKG", "model": "Citation XLS/XLS+", "departure_airport_iata": "OLB", "operatorId": "0012000000vixXYAAY", "seats": "8", "price": "10040", "manufacturer": "Cessna", "lastDepartureTime": "2018-08-26 23:50:00", "sfAircraftId": "a091r00001YcqYhAAJ", "firstDepartureTime": "2018-08-22 00:10:00"}, "11218": {"arrival_airport_iata": "KJK", "model": "Citation CJ4", "departure_airport_iata": "AGP", "operatorId": "0012000000AF9mOAAT", "seats": "7", "price": "12540", "manufacturer": "Cessna", "lastDepartureTime": "2018-08-30 23:50:00", "sfAircraftId": "a09w000001WUOdKAAX", "firstDepartureTime": "2018-08-30 00:10:00"}, "11219": {"arrival_airport_iata": "LIN", "model": "Citation X", "departure_airport_iata": "RTM", "operatorId": "0012000000EjRYgAAN", "seats": "8", "price": "8190", "manufacturer": "Cessna", "lastDepartureTime": "2018-08-22 23:50:00", "sfAircraftId": "a09w000000ZjaPbAAJ", "firstDepartureTime": "2018-08-19 00:10:00"}, "11637": {"arrival_airport_iata": "SJD", "model": "GIV-SP", "departure_airport_iata": "VNY", "operatorId": "0012000000JuBR7AAN", "seats": "14", "price": "20860", "manufacturer": "Gulfstream", "lastDepartureTime": "2018-06-24 23:50:00", "sfAircraftId": "a091r00001Xld72AAB", "firstDepartureTime": "2018-06-24 00:10:00"}, "11519": {"arrival_airport_iata": "ISP", "model": "G650", "departure_airport_iata": "STN", "operatorId": "0012000000LnxYnAAJ", "seats": "13", "price": "131080", "manufacturer": "Gulfstream", "lastDepartureTime": "2018-08-01 23:50:00", "sfAircraftId": "a09w000000bS8DSAA0", "firstDepartureTime": "2018-08-01 00:10:00"}, "11327": {"arrival_airport_iata": "IBZ", "model": "750", "departure_airport_iata": "BQH", "operatorId": "0012000000rauhDAAQ", "seats": "8", "price": "11880", "manufacturer": "Hawker Beechcraft", "lastDepartureTime": "2018-08-29 23:50:00", "sfAircraftId": "a09w000001C2o7fAAB", "firstDepartureTime": "2018-08-29 00:10:00"}, "11514": {"arrival_airport_iata": "GVA", "model": "Citation XLS/XLS+", "departure_airport_iata": "PRG", "operatorId": "0012000000KXPDVAA5", "seats": "8", "price": "5600", "manufacturer": "Cessna", "lastDepartureTime": "2018-05-30 23:50:00", "sfAircraftId": "a09w000000ZjeVfAAJ", "firstDepartureTime": "2018-05-30 00:10:00"}, "11616": {"arrival_airport_iata": "VNY", "model": "GIV", "departure_airport_iata": "GOA", "operatorId": "0012000000bSV9iAAG", "seats": "14", "price": "113130", "manufacturer": "Gulfstream", "lastDepartureTime": "2018-06-06 23:50:00", "sfAircraftId": "a09w000000Zjm85AAB", "firstDepartureTime": "2018-06-05 00:10:00"}, "11594": {"arrival_airport_iata": "JMK", "model": "GV", "departure_airport_iata": "TEB", "operatorId": "0012000000JuBR7AAN", "seats": "14", "price": "93590", "manufacturer": "Gulfstream", "lastDepartureTime": "2018-07-13 23:50:00", "sfAircraftId": "a09w000000ZkUluAAF", "firstDepartureTime": "2018-07-09 00:10:00"}, "11614": {"arrival_airport_iata": "HAM", "model": "Falcon 8X", "departure_airport_iata": "TEB", "operatorId": "0012000000EjRYeAAN", "seats": "15", "price": "69040", "manufacturer": "Dassault", "lastDepartureTime": "2018-06-08 23:50:00", "sfAircraftId": "a091r00001Xn6JsAAJ", "firstDepartureTime": "2018-06-06 00:10:00"}, "11615": {"arrival_airport_iata": "SXR", "model": "Citation X", "departure_airport_iata": "VKO", "operatorId": "0012000000hfRGCAA2", "seats": "8", "price": "27860", "manufacturer": "Cessna", "lastDepartureTime": "2018-06-08 23:50:00", "sfAircraftId": "a09w000000kSqX9AAK", "firstDepartureTime": "2018-06-06 00:10:00"}, "11612": {"arrival_airport_iata": "DWC", "model": "G450", "departure_airport_iata": "PEK", "operatorId": "0012000000zB408AAC", "seats": "13", "price": "72340", "manufacturer": "Gulfstream", "lastDepartureTime": "2018-06-05 23:50:00", "sfAircraftId": "a09w000000Zjb5XAAR", "firstDepartureTime": "2018-06-01 00:10:00"}, "11613": {"arrival_airport_iata": "VNY", "model": "Challenger 604", "departure_airport_iata": "NCE", "operatorId": "001w000001IcLXtAAN", "seats": "9", "price": "136620", "manufacturer": "Bombardier", "lastDepartureTime": "2018-06-04 23:50:00", "sfAircraftId": "a09w000000fAapuAAC", "firstDepartureTime": "2018-06-03 00:10:00"}, "11593": {"arrival_airport_iata": "FAB", "model": "GIV-SP", "departure_airport_iata": "TEB", "operatorId": "0012000000JuBR7AAN", "seats": "14", "price": "59540", "manufacturer": "Gulfstream", "lastDepartureTime": "2018-07-26 23:50:00", "sfAircraftId": "a091r00001Xld72AAB", "firstDepartureTime": "2018-07-23 00:10:00"}, "11592": {"arrival_airport_iata": "TEB", "model": "GIV-SP", "departure_airport_iata": "FAB", "operatorId": "0012000000JuBR7AAN", "seats": "14", "price": "66000", "manufacturer": "Gulfstream", "lastDepartureTime": "2018-07-13 23:50:00", "sfAircraftId": "a091r00001Xld72AAB", "firstDepartureTime": "2018-07-09 00:10:00"}, "11599": {"arrival_airport_iata": "VKO", "model": "ACJ319", "departure_airport_iata": "DWC", "operatorId": "0012000000AFXRuAAP", "seats": "19", "price": "142500", "manufacturer": "Airbus", "lastDepartureTime": "2018-07-15 23:50:00", "sfAircraftId": "a09w000000ZkZltAAF", "firstDepartureTime": "2018-07-15 00:10:00"}, "11098": {"arrival_airport_iata": "TRF", "model": "Legacy 650", "departure_airport_iata": "LIN", "operatorId": "0012000000EjRYgAAN", "seats": "13", "price": "19140", "manufacturer": "Embraer", "lastDepartureTime": "2018-07-26 23:50:00", "sfAircraftId": "a09w000000ZjaPCAAZ", "firstDepartureTime": "2018-07-24 00:10:00"}, "11225": {"arrival_airport_iata": "BQH", "model": "Citation XLS/XLS+", "departure_airport_iata": "GVA", "operatorId": "0012000000QTlocAAD", "seats": "8", "price": "7790", "manufacturer": "Cessna", "lastDepartureTime": "2018-08-06 23:50:00", "sfAircraftId": "a09w000000s7rbCAAQ", "firstDepartureTime": "2018-08-06 00:10:00"}, "11224": {"arrival_airport_iata": "NCE", "model": "Citation XLS/XLS+", "departure_airport_iata": "LUX", "operatorId": "0012000000KVL7VAAX", "seats": "8", "price": "7000", "manufacturer": "Cessna", "lastDepartureTime": "2018-08-16 23:50:00", "sfAircraftId": "a09w000000bPKKpAAO", "firstDepartureTime": "2018-08-16 00:10:00"}, "11223": {"arrival_airport_iata": "FLR", "model": "Phenom 300", "departure_airport_iata": "BQH", "operatorId": "0012000000QTlocAAD", "seats": "7", "price": "10300", "manufacturer": "Embraer", "lastDepartureTime": "2018-08-18 23:50:00", "sfAircraftId": "a09w000000s9fzfAAA", "firstDepartureTime": "2018-08-18 00:10:00"}, "11222": {"arrival_airport_iata": "BQH", "model": "Citation XLS/XLS+", "departure_airport_iata": "FLR", "operatorId": "0012000000QTlocAAD", "seats": "8", "price": "10830", "manufacturer": "Cessna", "lastDepartureTime": "2018-08-11 23:50:00", "sfAircraftId": "a09w000000s7rbCAAQ", "firstDepartureTime": "2018-08-11 00:10:00"}, "11220": {"arrival_airport_iata": "OBF", "model": "Citation CJ2/CJ2+", "departure_airport_iata": "MLH", "operatorId": "0012000000AFXS2AAP", "seats": "6", "price": "3570", "manufacturer": "Cessna", "lastDepartureTime": "2018-08-12 23:50:00", "sfAircraftId": "a09w000000ZjYKFAA3", "firstDepartureTime": "2018-08-12 00:10:00"}, "11151": {"arrival_airport_iata": "LIN", "model": "Phenom 300", "departure_airport_iata": "JMK", "operatorId": "0012000000EjRYgAAN", "seats": "7", "price": "14130", "manufacturer": "Embraer", "lastDepartureTime": "2018-09-05 23:50:00", "sfAircraftId": "a09w000000ZjZZfAAN", "firstDepartureTime": "2018-09-02 00:00:00"}, "11019": {"arrival_airport_iata": "BRE", "model": "Citation XLS/XLS+", "departure_airport_iata": "PMI", "operatorId": "00120000012NwZlAAK", "seats": "8", "price": "12680", "manufacturer": "Cessna", "lastDepartureTime": "2018-06-07 23:50:00", "sfAircraftId": "a09w000000ZkJ02AAF", "firstDepartureTime": "2018-06-07 00:10:00"}, "11506": {"arrival_airport_iata": "PMI", "model": "Challenger 300", "departure_airport_iata": "BQH", "operatorId": "001w000001AKVAOAA5", "seats": "9", "price": "10400", "manufacturer": "Bombardier", "lastDepartureTime": "2018-09-01 12:00:00", "sfAircraftId": "a09w000000ZjZq7AAF", "firstDepartureTime": "2018-09-01 00:10:00"}, "11505": {"arrival_airport_iata": "BQH", "model": "Phenom 100", "departure_airport_iata": "ANR", "operatorId": "001w000001AKVAOAA5", "seats": "4", "price": "3440", "manufacturer": "Embraer", "lastDepartureTime": "2018-07-14 23:50:00", "sfAircraftId": "a09w000001WSbKoAAL", "firstDepartureTime": "2018-07-14 14:00:00"}, "11627": {"arrival_airport_iata": "VKO", "model": "Global 6000", "departure_airport_iata": "XSP", "operatorId": "0012000000AFXSnAAP", "seats": "14", "price": "113790", "manufacturer": "Bombardier", "lastDepartureTime": "2018-06-01 23:50:00", "sfAircraftId": "a091r00001YeYYPAA3", "firstDepartureTime": "2018-05-28 00:10:00"}, "11626": {"arrival_airport_iata": "PEK", "model": "Global 6000", "departure_airport_iata": "UUS", "operatorId": "0012000000AFXSnAAP", "seats": "14", "price": "36300", "manufacturer": "Bombardier", "lastDepartureTime": "2018-06-01 23:50:00", "sfAircraftId": "a091r00001YeYYPAA3", "firstDepartureTime": "2018-05-29 00:10:00"}, "11624": {"arrival_airport_iata": "IEV", "model": "Citation Sovereign", "departure_airport_iata": "TLV", "operatorId": "001w00000196PZ6AAM", "seats": "8", "price": "16900", "manufacturer": "Cessna", "lastDepartureTime": "2018-05-30 23:50:00", "sfAircraftId": "a09w000000bQpBGAA0", "firstDepartureTime": "2018-05-27 00:10:00"}, "11421": {"arrival_airport_iata": "LIN", "model": "Citation CJ3", "departure_airport_iata": "DUB", "operatorId": "0012000000EjRYgAAN", "seats": "7", "price": "5420", "manufacturer": "Cessna", "lastDepartureTime": "2018-06-05 23:50:00", "sfAircraftId": "a09w000000ZjaPgAAJ", "firstDepartureTime": "2018-06-02 00:10:00"}, "11420": {"arrival_airport_iata": "LIN", "model": "Citation CJ3", "departure_airport_iata": "BHX", "operatorId": "0012000000EjRYgAAN", "seats": "7", "price": "5420", "manufacturer": "Cessna", "lastDepartureTime": "2018-06-13 23:50:00", "sfAircraftId": "a09w000000ZjaPgAAJ", "firstDepartureTime": "2018-06-10 00:10:00"}, "11629": {"arrival_airport_iata": "LBV", "model": "Falcon 900", "departure_airport_iata": "TMR", "operatorId": "0012000000AF9mjAAD", "seats": "14", "price": "29310", "manufacturer": "Dassault", "lastDepartureTime": "2018-06-02 23:50:00", "sfAircraftId": "a09w000000s9c0UAAQ", "firstDepartureTime": "2018-06-02 00:10:00"}, "11425": {"arrival_airport_iata": "VIE", "model": "Citation CJ2/CJ2+", "departure_airport_iata": "ATH", "operatorId": "0012000000IIRuoAAH", "seats": "6", "price": "5060", "manufacturer": "Cessna", "lastDepartureTime": "2018-06-04 23:50:00", "sfAircraftId": "a09w000000ZmEe5AAF", "firstDepartureTime": "2018-06-02 00:10:00"}, "11424": {"arrival_airport_iata": "LIN", "model": "Legacy 650", "departure_airport_iata": "BJV", "operatorId": "0012000000EjRYgAAN", "seats": "13", "price": "15800", "manufacturer": "Embraer", "lastDepartureTime": "2018-06-14 23:50:00", "sfAircraftId": "a09w000000dll9uAAA", "firstDepartureTime": "2018-06-12 00:10:00"}, "11331": {"arrival_airport_iata": "LTN", "model": "GIV", "departure_airport_iata": "TEB", "operatorId": "0012000000N8XjsAAF", "seats": "14", "price": "57420", "manufacturer": "Gulfstream", "lastDepartureTime": "2018-09-21 23:50:00", "sfAircraftId": "a09w0000011xuffAAA", "firstDepartureTime": "2018-09-17 00:10:00"}, "11330": {"arrival_airport_iata": "OLB", "model": "Citation CJ2/CJ2+", "departure_airport_iata": "VIE", "operatorId": "0012000000IIRuoAAH", "seats": "6", "price": "7000", "manufacturer": "Cessna", "lastDepartureTime": "2018-09-08 23:50:00", "sfAircraftId": "a09w000000ZmEe5AAF", "firstDepartureTime": "2018-09-05 00:10:00"}, "11338": {"arrival_airport_iata": "GVA", "model": "Falcon 2000LX", "departure_airport_iata": "VKO", "operatorId": "0012000000AF9muAAD", "seats": "10", "price": "24160", "manufacturer": "Dassault", "lastDepartureTime": "2018-10-15 23:50:00", "sfAircraftId": "a09w000000Zk4Y7AAJ", "firstDepartureTime": "2018-10-15 00:10:00"}, "11235": {"arrival_airport_iata": "GWT", "model": "Citation CJ2/CJ2+", "departure_airport_iata": "LIN", "operatorId": "0012000000EjRYgAAN", "seats": "6", "price": "7530", "manufacturer": "Cessna", "lastDepartureTime": "2018-06-06 23:50:00", "sfAircraftId": "a09w000000c7XiKAAU", "firstDepartureTime": "2018-06-05 00:10:00"}, "10848": {"arrival_airport_iata": "LBG", "model": "Citation XLS/XLS+", "departure_airport_iata": "VLC", "operatorId": "00120000012NwZlAAK", "seats": "8", "price": "6340", "manufacturer": "Cessna", "lastDepartureTime": "2018-06-21 23:50:00", "sfAircraftId": "a09w000000ZkJ02AAF", "firstDepartureTime": "2018-06-21 00:00:00"}, "11532": {"arrival_airport_iata": "EFL", "model": "Citation Bravo", "departure_airport_iata": "OXF", "operatorId": "001w00000197POSAA2", "seats": "7", "price": "13600", "manufacturer": "Cessna", "lastDepartureTime": "2018-06-01 23:50:00", "sfAircraftId": "a09w000000bQyxgAAC", "firstDepartureTime": "2018-05-31 00:10:00"}, "11531": {"arrival_airport_iata": "LIN", "model": "Citation CJ1/CJ1+", "departure_airport_iata": "LBG", "operatorId": "001w000001GbHkmAAF", "seats": "5", "price": "4690", "manufacturer": "Cessna", "lastDepartureTime": "2018-06-01 23:50:00", "sfAircraftId": "a09w000000bS1JYAA0", "firstDepartureTime": "2018-05-31 00:10:00"}, "11530": {"arrival_airport_iata": "YYZ", "model": "GIV", "departure_airport_iata": "TEB", "operatorId": "0012000000bSV9iAAG", "seats": "14", "price": "11620", "manufacturer": "Gulfstream", "lastDepartureTime": "2018-05-31 23:50:00", "sfAircraftId": "a09w000000bP3paAAC", "firstDepartureTime": "2018-05-31 00:10:00"}, "11537": {"arrival_airport_iata": "VNY", "model": "G550", "departure_airport_iata": "XSP", "operatorId": "0012000000N8XjsAAF", "seats": "14", "price": "162890", "manufacturer": "Gulfstream", "lastDepartureTime": "2018-06-03 23:50:00", "sfAircraftId": "a09w000000bP1bYAAS", "firstDepartureTime": "2018-05-30 00:10:00"}, "11536": {"arrival_airport_iata": "PMI", "model": "Legacy 650", "departure_airport_iata": "GVA", "operatorId": "0012000000EjRYgAAN", "seats": "13", "price": "12540", "manufacturer": "Embraer", "lastDepartureTime": "2018-06-03 23:50:00", "sfAircraftId": "a09w000000ZjaPCAAZ", "firstDepartureTime": "2018-06-01 00:10:00"}, "11535": {"arrival_airport_iata": "JED", "model": "Global 6000", "departure_airport_iata": "LBG", "operatorId": "0012000000AF9mtAAD", "seats": "14", "price": "59900", "manufacturer": "Bombardier", "lastDepartureTime": "2018-06-02 23:50:00", "sfAircraftId": "a09w000000mVOXEAA4", "firstDepartureTime": "2018-06-02 00:10:00"}, "11534": {"arrival_airport_iata": "FAO", "model": "Legacy 650", "departure_airport_iata": "LIN", "operatorId": "0012000000EjRYgAAN", "seats": "13", "price": "20990", "manufacturer": "Embraer", "lastDepartureTime": "2018-06-02 23:50:00", "sfAircraftId": "a09w000001C2CjEAAV", "firstDepartureTime": "2018-06-02 00:10:00"}, "11418": {"arrival_airport_iata": "IBZ", "model": "Learjet 75", "departure_airport_iata": "MAN", "operatorId": "001w0000015WwFwAAK", "seats": "8", "price": "7360", "manufacturer": "Bombardier", "lastDepartureTime": "2018-06-02 23:50:00", "sfAircraftId": "a09w000000c6YyIAAU", "firstDepartureTime": "2018-06-02 00:10:00"}, "11638": {"arrival_airport_iata": "MRS", "model": "G550", "departure_airport_iata": "VNY", "operatorId": "0012000000JuBR7AAN", "seats": "14", "price": "112600", "manufacturer": "Gulfstream", "lastDepartureTime": "2018-07-02 23:50:00", "sfAircraftId": "a09w000000ZkYx8AAF", "firstDepartureTime": "2018-06-27 00:10:00"}, "11639": {"arrival_airport_iata": "JMK", "model": "GV", "departure_airport_iata": "TEB", "operatorId": "0012000000JuBR7AAN", "seats": "14", "price": "130680", "manufacturer": "Gulfstream", "lastDepartureTime": "2018-07-13 23:50:00", "sfAircraftId": "a09w000000ZkUluAAF", "firstDepartureTime": "2018-07-09 00:00:00"}, "11634": {"arrival_airport_iata": "SXM", "model": "Falcon 7X", "departure_airport_iata": "ANR", "operatorId": "0012000000AF9mlAAD", "seats": "14", "price": "82900", "manufacturer": "Dassault", "lastDepartureTime": "2018-06-14 23:50:00", "sfAircraftId": "a09w000000ZjYzDAAV", "firstDepartureTime": "2018-06-10 00:10:00"}, "11636": {"arrival_airport_iata": "PNE", "model": "900XP", "departure_airport_iata": "CTG", "operatorId": "001w000001Onux9AAB", "seats": "8", "price": "27590", "manufacturer": "Hawker Beechcraft", "lastDepartureTime": "2018-06-09 23:50:00", "sfAircraftId": "a09w000001C4QeKAAV", "firstDepartureTime": "2018-06-06 00:10:00"}, "11431": {"arrival_airport_iata": "SFO", "model": "GV", "departure_airport_iata": "PEK", "operatorId": "0012000000MIDeuAAH", "seats": "14", "price": "97420", "manufacturer": "Gulfstream", "lastDepartureTime": "2018-05-30 23:50:00", "sfAircraftId": "a09w000001C2TUkAAN", "firstDepartureTime": "2018-05-28 00:10:00"}, "11633": {"arrival_airport_iata": "TEB", "model": "GIV", "departure_airport_iata": "GRO", "operatorId": "0012000000bSV9iAAG", "seats": "14", "price": "73130", "manufacturer": "Gulfstream", "lastDepartureTime": "2018-06-03 23:50:00", "sfAircraftId": "a09w000000Zjm85AAB", "firstDepartureTime": "2018-06-02 00:10:00"}, "11520": {"arrival_airport_iata": "DPS", "model": "G550", "departure_airport_iata": "MCT", "operatorId": "0012000000RLdvKAAT", "seats": "14", "price": "72300", "manufacturer": "Gulfstream", "lastDepartureTime": "2018-08-15 23:50:00", "sfAircraftId": "a09w000000jDyJDAA0", "firstDepartureTime": "2018-08-15 00:10:00"}, "11162": {"arrival_airport_iata": "PMI", "model": "850XP", "departure_airport_iata": "BMA", "operatorId": "001w0000015WQz0AAG", "seats": "8", "price": "18220", "manufacturer": "Hawker Beechcraft", "lastDepartureTime": "2018-07-15 23:50:00", "sfAircraftId": "a09w000000j3BwtAAE", "firstDepartureTime": "2018-07-13 00:10:00"}, "11328": {"arrival_airport_iata": "VLC", "model": "Citation XLS/XLS+", "departure_airport_iata": "ZQC", "operatorId": "001w0000015TdGLAA0", "seats": "8", "price": "11220", "manufacturer": "Cessna", "lastDepartureTime": "2018-09-06 23:50:00", "sfAircraftId": "a09w000000mViEWAA0", "firstDepartureTime": "2018-09-06 00:10:00"}, "11329": {"arrival_airport_iata": "FAO", "model": "G200", "departure_airport_iata": "LBA", "operatorId": "001w000001IBUdtAAH", "seats": "9", "price": "17160", "manufacturer": "Gulfstream", "lastDepartureTime": "2018-08-31 23:50:00", "sfAircraftId": "a09w000000fA9juAAC", "firstDepartureTime": "2018-08-30 00:10:00"}, "11529": {"arrival_airport_iata": "THA", "model": "Learjet 45XR", "departure_airport_iata": "FXE", "operatorId": "0012000000AFXS9AAP", "seats": "8", "price": "11750", "manufacturer": "Bombardier", "lastDepartureTime": "2018-05-31 23:50:00", "sfAircraftId": "a09w000001C2mIQAAZ", "firstDepartureTime": "2018-05-31 00:10:00"}, "11170": {"arrival_airport_iata": "NCE", "model": "Legacy 450", "departure_airport_iata": "BRE", "operatorId": "00120000012NwZlAAK", "seats": "7", "price": "11490", "manufacturer": "Embraer", "lastDepartureTime": "2018-07-29 23:50:00", "sfAircraftId": "a09w000001C2mxEAAR", "firstDepartureTime": "2018-07-26 00:10:00"}, "11408": {"arrival_airport_iata": "LBA", "model": "Premier 1A", "departure_airport_iata": "NCE", "operatorId": "001w000001XVZeTAAX", "seats": "6", "price": "5720", "manufacturer": "Hawker Beechcraft", "lastDepartureTime": "2018-06-09 23:50:00", "sfAircraftId": "a09w000001C2413AAB", "firstDepartureTime": "2018-06-09 00:10:00"}, "11649": {"arrival_airport_iata": "BHX", "model": "Citation XLS/XLS+", "departure_airport_iata": "OLB", "operatorId": "0012000000G1IskAAF", "seats": "8", "price": "12020", "manufacturer": "Cessna", "lastDepartureTime": "2018-06-30 23:50:00", "sfAircraftId": "a09w000000djrBDAAY", "firstDepartureTime": "2018-06-30 00:10:00"}, "11591": {"arrival_airport_iata": "BQH", "model": "G550", "departure_airport_iata": "VNY", "operatorId": "0012000000JuBR7AAN", "seats": "14", "price": "102700", "manufacturer": "Gulfstream", "lastDepartureTime": "2018-06-30 23:50:00", "sfAircraftId": "a09w000001C27WCAAZ", "firstDepartureTime": "2018-06-27 00:20:00"}, "10768": {"arrival_airport_iata": "BHX", "model": "Phenom 300", "departure_airport_iata": "BIA", "operatorId": "0012000000EjRYgAAN", "seats": "7", "price": "12020", "manufacturer": "Embraer", "lastDepartureTime": "2018-06-10 23:50:00", "sfAircraftId": "a09w000000ZjZZfAAN", "firstDepartureTime": "2018-06-09 00:10:00"}, "11645": {"arrival_airport_iata": "DYU", "model": "G650", "departure_airport_iata": "LBG", "operatorId": "0012000000QSrlbAAD", "seats": "13", "price": "60830", "manufacturer": "Gulfstream", "lastDepartureTime": "2018-05-30 23:50:00", "sfAircraftId": "a091r00001YplWFAAZ", "firstDepartureTime": "2018-05-28 00:10:00"}, "11611": {"arrival_airport_iata": "SFO", "model": "Falcon 2000", "departure_airport_iata": "LBG", "operatorId": "0012000000EjRYeAAN", "seats": "10", "price": "73660", "manufacturer": "Dassault", "lastDepartureTime": "2018-06-05 23:50:00", "sfAircraftId": "a09w000000bQQlcAAG", "firstDepartureTime": "2018-06-02 00:10:00"}, "11551": {"arrival_airport_iata": "FXE", "model": "GIV", "departure_airport_iata": "HOU", "operatorId": "0012000000hfRGCAA2", "seats": "14", "price": "20200", "manufacturer": "Gulfstream", "lastDepartureTime": "2018-06-17 23:50:00", "sfAircraftId": "a09w000000ZjpgsAAB", "firstDepartureTime": "2018-06-17 00:10:00"}, "11550": {"arrival_airport_iata": "TEB", "model": "GV", "departure_airport_iata": "FLR", "operatorId": "0012000000hfRGCAA2", "seats": "14", "price": "87780", "manufacturer": "Gulfstream", "lastDepartureTime": "2018-07-23 23:50:00", "sfAircraftId": "a09w000001XBZieAAH", "firstDepartureTime": "2018-07-21 00:10:00"}, "11423": {"arrival_airport_iata": "BQH", "model": "Learjet 75", "departure_airport_iata": "LIN", "operatorId": "001w0000015WwFwAAK", "seats": "8", "price": "6260", "manufacturer": "Bombardier", "lastDepartureTime": "2018-06-14 23:50:00", "sfAircraftId": "a09w000000c6YyIAAU", "firstDepartureTime": "2018-06-14 00:10:00"}, "11412": {"arrival_airport_iata": "HAM", "model": "Citation CJ2/CJ2+", "departure_airport_iata": "PMI", "operatorId": "0012000000EjRYgAAN", "seats": "6", "price": "5810", "manufacturer": "Cessna", "lastDepartureTime": "2018-05-30 23:50:00", "sfAircraftId": "a09w000000ZkilpAAB", "firstDepartureTime": "2018-05-25 00:10:00"}, "11413": {"arrival_airport_iata": "HER", "model": "Citation CJ3", "departure_airport_iata": "LIN", "operatorId": "0012000000EjRYgAAN", "seats": "7", "price": "13600", "manufacturer": "Cessna", "lastDepartureTime": "2018-06-09 23:50:00", "sfAircraftId": "a09w000000ZjaPgAAJ", "firstDepartureTime": "2018-06-07 00:10:00"}, "11168": {"arrival_airport_iata": "OXF", "model": "Citation Bravo", "departure_airport_iata": "NCE", "operatorId": "001w00000197POSAA2", "seats": "7", "price": "7530", "manufacturer": "Cessna", "lastDepartureTime": "2018-07-27 23:50:00", "sfAircraftId": "a09w000000bQyxgAAC", "firstDepartureTime": "2018-07-26 00:10:00"}, "11169": {"arrival_airport_iata": "MAD", "model": "G200", "departure_airport_iata": "VIE", "operatorId": "0012000000IIRuoAAH", "seats": "9", "price": "16500", "manufacturer": "Gulfstream", "lastDepartureTime": "2018-07-21 23:50:00", "sfAircraftId": "a09w000000Zm68QAAR", "firstDepartureTime": "2018-07-18 00:10:00"}, "11417": {"arrival_airport_iata": "CEQ", "model": "Phenom 300", "departure_airport_iata": "FAB", "operatorId": "0012000000EjRYgAAN", "seats": "7", "price": "7720", "manufacturer": "Embraer", "lastDepartureTime": "2018-06-06 23:50:00", "sfAircraftId": "a09w000000ZjZZfAAN", "firstDepartureTime": "2018-06-05 00:10:00"}, "11164": {"arrival_airport_iata": "STR", "model": "Citation CJ4", "departure_airport_iata": "LYN", "operatorId": "0012000000JtbOVAAZ", "seats": "7", "price": "5420", "manufacturer": "Cessna", "lastDepartureTime": "2018-07-29 23:50:00", "sfAircraftId": "a09w000000fBPEwAAO", "firstDepartureTime": "2018-07-28 00:10:00"}, "11165": {"arrival_airport_iata": "STR", "model": "Citation CJ4", "departure_airport_iata": "IBZ", "operatorId": "0012000000JtbOVAAZ", "seats": "7", "price": "8850", "manufacturer": "Cessna", "lastDepartureTime": "2018-07-04 23:50:00", "sfAircraftId": "a09w000000ZmGyHAAV", "firstDepartureTime": "2018-07-02 00:10:00"}, "11166": {"arrival_airport_iata": "BQH", "model": "850XP", "departure_airport_iata": "NCY", "operatorId": "0012000000rauhDAAQ", "seats": "8", "price": "8190", "manufacturer": "Hawker Beechcraft", "lastDepartureTime": "2018-07-22 23:50:00", "sfAircraftId": "a09w000000c7dQfAAI", "firstDepartureTime": "2018-07-20 00:10:00"}, "11167": {"arrival_airport_iata": "BLL", "model": "4000", "departure_airport_iata": "PMI", "operatorId": "0012000000G1IJlAAN", "seats": "8", "price": "19140", "manufacturer": "Hawker Beechcraft", "lastDepartureTime": "2018-07-08 23:50:00", "sfAircraftId": "a09w000001C50dFAAR", "firstDepartureTime": "2018-07-06 00:10:00"}, "11161": {"arrival_airport_iata": "FRA", "model": "Global 5000", "departure_airport_iata": "GVA", "operatorId": "0012000000zB408AAC", "seats": "13", "price": "10430", "manufacturer": "Bombardier", "lastDepartureTime": "2018-07-10 23:50:00", "sfAircraftId": "a09w000000Zjb37AAB", "firstDepartureTime": "2018-07-07 00:10:00"}, "11399": {"arrival_airport_iata": "LTN", "model": "Legacy 650", "departure_airport_iata": "GVA", "operatorId": "0012000000G1IskAAF", "seats": "13", "price": "11880", "manufacturer": "Embraer", "lastDepartureTime": "2018-05-30 23:50:00", "sfAircraftId": "a09w000000ZjZqbAAF", "firstDepartureTime": "2018-05-26 00:10:00"}, "11163": {"arrival_airport_iata": "PSA", "model": "Citation CJ2/CJ2+", "departure_airport_iata": "BRS", "operatorId": "0012000000IHYu1AAH", "seats": "6", "price": "7260", "manufacturer": "Cessna", "lastDepartureTime": "2018-07-17 23:50:00", "sfAircraftId": "a09w000000Zjat7AAB", "firstDepartureTime": "2018-07-14 00:10:00"}, "10773": {"arrival_airport_iata": "LBG", "model": "Citation Mustang", "departure_airport_iata": "VLC", "operatorId": "001w0000014VuzxAAC", "seats": "4", "price": "7000", "manufacturer": "Cessna", "lastDepartureTime": "2018-06-12 23:50:00", "sfAircraftId": "a09w000000ZjagcAAB", "firstDepartureTime": "2018-06-12 00:10:00"}, "10771": {"arrival_airport_iata": "IBZ", "model": "Citation CJ2/CJ2+", "departure_airport_iata": "LIN", "operatorId": "0012000000EjRYgAAN", "seats": "6", "price": "7000", "manufacturer": "Cessna", "lastDepartureTime": "2018-06-23 23:50:00", "sfAircraftId": "a09w000000c7XiKAAU", "firstDepartureTime": "2018-06-21 00:10:00"}, "10777": {"arrival_airport_iata": "OSL", "model": "Citation Sovereign", "departure_airport_iata": "CIA", "operatorId": "0012000000EjRZAAA3", "seats": "8", "price": "16900", "manufacturer": "Cessna", "lastDepartureTime": "2018-06-22 23:50:00", "sfAircraftId": "a09w000000Zjl7uAAB", "firstDepartureTime": "2018-06-22 00:10:00"}, "10775": {"arrival_airport_iata": "BRE", "model": "Citation XLS/XLS+", "departure_airport_iata": "SIR", "operatorId": "00120000012NwZlAAK", "seats": "8", "price": "7790", "manufacturer": "Cessna", "lastDepartureTime": "2018-06-09 23:50:00", "sfAircraftId": "a09w0000011yFsUAAU", "firstDepartureTime": "2018-06-09 00:10:00"}, "11652": {"arrival_airport_iata": "CEQ", "model": "Legacy 450", "departure_airport_iata": "GVA", "operatorId": "0012000000Irg1FAAR", "seats": "7", "price": "5060", "manufacturer": "Embraer", "lastDepartureTime": "2018-06-01 23:50:00", "sfAircraftId": "a09w000000s8rRpAAI", "firstDepartureTime": "2018-05-29 00:10:00"}, "11653": {"arrival_airport_iata": "SOF", "model": "Avanti P180", "departure_airport_iata": "GVA", "operatorId": "0012000000VB6FqAAL", "seats": "7", "price": "9020", "manufacturer": "Piaggio", "lastDepartureTime": "2018-05-30 23:50:00", "sfAircraftId": "a09w000000ZkIdMAAV", "firstDepartureTime": "2018-05-30 00:10:00"}, "11650": {"arrival_airport_iata": "NHT", "model": "400XP", "departure_airport_iata": "NCE", "operatorId": "001w000001ew8e1AAA", "seats": "7", "price": "7790", "manufacturer": "Hawker Beechcraft", "lastDepartureTime": "2018-07-31 23:50:00", "sfAircraftId": "a09w000001WShELAA1", "firstDepartureTime": "2018-07-28 00:10:00"}, "10779": {"arrival_airport_iata": "AGP", "model": "Citation CJ2/CJ2+", "departure_airport_iata": "BRS", "operatorId": "0012000000IHYu1AAH", "seats": "6", "price": "9770", "manufacturer": "Cessna", "lastDepartureTime": "2018-10-12 23:50:00", "sfAircraftId": "a09w000000ZjatHAAR", "firstDepartureTime": "2018-10-12 00:10:00"}}